pylearn_ai/__init__.py
pylearn_ai/core/__init__.py
pylearn_ai/core/algorithms.py
pylearn_ai/core/structures.py
pylearn_ai/core/unitframe.py
pylearn_ai/neural/__init__.py
pylearn_ai/neural/cnn.py
pylearn_ai/neural/gat.py
pylearn_ai/neural/gcn.py
pylearn_ai/neural/gin.py
pylearn_ai/neural/mlp.py
pylearn_ai/reinforcement/__init__.py
pylearn_ai/reinforcement/policy_optimization.py
pylearn_ai/reinforcement/q_learning.py
pylearn_ai/supervised/__init__.py
pylearn_ai/supervised/linear_regression.py
pylearn_ai/supervised/logistic_regression.py
pylearn_ai/supervised/tree_classifier.py
pylearn_ai/supervised/tree_regression.py
pylearn_ai/unsupervised/__init__.py
pylearn_ai/unsupervised/hierarchical.py
pylearn_ai/unsupervised/k-means.py
pylearn_ai/utils/__init__.py
pylearn_ai/utils/activations.py
pylearn_ai/utils/logging.py
pylearn_ai/utils/loss.py
pylearn_ai/utils/metrics.py
pylearn_ai/utils/optimizer.py
pylearn_ai/utils/preprocessing.py
tests/__init__.py
tests/test.py
pylearn_ai-0.1.0b3.dist-info/LICENSE
pylearn_ai-0.1.0b3.dist-info/METADATA
pylearn_ai-0.1.0b3.dist-info/WHEEL
pylearn_ai-0.1.0b3.dist-info/top_level.txt
pylearn_ai-0.1.0b3.dist-info/RECORD
