Metadata-Version: 2.2
Name: PyLearn-AI
Version: 0.1.0b3
Summary: A pure-Python machine learning and deep learning framework with no external dependencies.
Home-page: https://github.com/ramosv/PyLearn-AI
Author: Vicente Ramos
Author-email: vicente.ramos@ucdenver.edu
License: MIT
Classifier: Development Status :: 3 - Alpha
Classifier: Intended Audience :: Developers
Classifier: Intended Audience :: Science/Research
Classifier: License :: OSI Approved :: MIT License
Classifier: Programming Language :: Python :: 3.10
Classifier: Topic :: Scientific/Engineering :: Artificial Intelligence
Requires-Python: >=3.10
License-File: LICENSE
Provides-Extra: docs
Requires-Dist: sphinx; extra == "docs"
Provides-Extra: tests
Requires-Dist: pytest; extra == "tests"
